extracted_frames/__init__.py
extracted_frames/main.py
extractedframes-1.0.0.dist-info/licenses/LICENSE
extractedframes-1.0.0.dist-info/METADATA
extractedframes-1.0.0.dist-info/WHEEL
extractedframes-1.0.0.dist-info/entry_points.txt
extractedframes-1.0.0.dist-info/top_level.txt
extractedframes-1.0.0.dist-info/RECORD
