Metadata-Version: 2.4
Name: extractedframes
Version: 1.0.0
Summary: CLI tool to extract frames from videos
Author-email: Daniel <grabardm@ml-dev.ru>
License-Expression: MIT
Project-URL: Homepage, https://github.com/Daniel-Robotic/ExtractedFrames
Project-URL: Source, https://github.com/Daniel-Robotic/ExtractedFrames
Project-URL: Tracker, https://github.com/Daniel-Robotic/ExtractedFrames/issues
Requires-Python: >=3.12
License-File: LICENSE
Requires-Dist: opencv-python>=4.12.0.88
Dynamic: license-file
